[
  {
    "item": "betal leaf miang with local dungeness crab",
    "description": "ginger, lime, peanuts, toasted coconut, caramelized palm sugar, galangal dressing",
    "price": 14,
    "meal": "dinner",
    "course": "appetizer",
    "item_id": 3001
  },
  {
    "item": "steamed mussels with lemongrass and thai basil",
    "description": "served with nahm jim sauce",
    "price": 14,
    "meal": "dinner",
    "course": "appetizer",
    "item_id": 3002
  },
  {
    "item": "grilled thai sausage and crispy rice salad",
    "description": "house fermented pork sausage, crispy curried rice puffs, coriander, lemongrass, ginger, fried shallots",
    "price": 14,
    "meal": "dinner",
    "course": "appetizer",
    "item_id": 3003
  },
  {
    "item": "brussel sprout salad",
    "description": "lime juice, chili flakes, toasted almonds, garlic oil",
    "price": 14,
    "meal": "dinner",
    "course": "appetizer",
    "item_id": 3004
  },
  {
    "item": "tom gati of coconut and chicken soup",
    "description": "galangal, lemongrass, young coconut, variety of mushrooms, chili jam (serves 2 peopls)",
    "price": 19,
    "meal": "dinner",
    "course": "appetizer",
    "item_id": 3005
  },
  {
    "item": "hot and sour soup of baby pork rib",
    "description": "fresh young baby corn, dried orange peel and fried garlic (serves 2 people)",
    "price": 19,
    "meal": "dinner",
    "course": "appetizer",
    "item_id": 3006
  },
  {
    "item": "hot and sour cloudy prawn soup",
    "description": "chilli jam, oyster mushrooms with sustainable prawns (serves 2 people)",
    "price": 19,
    "meal": "dinner",
    "course": "appetizer",
    "item_id": 3007
  },
  {
    "item": "glorious greens organic salad",
    "description": "changing daily, hand picked fresh greens, herbs and edible flowers, nahm jim-olive oil dressing",
    "price": 14,
    "meal": "dinner",
    "course": "appetizer",
    "item_id": 3008
  },
  {
    "item": "thai style crispy chicken wings",
    "description": "served with nam jim jeaw, tamarind dipping sauce",
    "price": 14,
    "meal": "dinner",
    "course": "appetizer",
    "item_id": 3009
  },
  {
    "item": "grilled wild sockeye salmon salad",
    "description": "lemongrass, nahm jim dressing, lime leaf, fresh herbs and roasted peanuts",
    "price": 21,
    "meal": "dinner",
    "course": "main",
    "item_id": 3010
  },
  {
    "item": "crispy water spinach salad",
    "description": "water spinach deep fried with rice flour and coconut cream batter, cashew, green mango, coriander dressing",
    "price": 18,
    "meal": "dinner",
    "course": "main",
    "item_id": 3011
  },
  {
    "item": "duck leg confit salad",
    "description": "fresh herbs, fried shallots, sesame seed, longan, palm sugar and tamarind dressing",
    "price": 20,
    "meal": "dinner",
    "course": "main",
    "item_id": 3012
  },
  {
    "item": "8 spice ling cod",
    "description": "caramelized palm sugar and tamarind sauce, crispy ling cod, fried thai spices and aromatics",
    "price": 21,
    "meal": "dinner",
    "course": "main",
    "item_id": 3013
  },
  {
    "item": "pad thai",
    "description": "fresh rice noodles, tamarind, peanuts, tofu, egg, prawns",
    "price": 18,
    "meal": "dinner",
    "course": "main",
    "item_id": 3014
  },
  {
    "item": "3 flavour baby back pork rib",
    "description": "fresh baby corn, green peppercorn, long bean, thai basil",
    "price": 21,
    "meal": "dinner",
    "course": "main",
    "item_id": 3015
  },
  {
    "item": "thai long green eggplant & pork stir fry",
    "description": "bird's eye chilies, fermented soy bean paste, fried thai baby garlic",
    "price": 20,
    "meal": "dinner",
    "course": "main",
    "item_id": 3016
  },
  {
    "item": "gang kau, tumeric curry of grilled striplion beef",
    "description": "rich and flavourful curry with kale, shrimp paste and shredded wild ginger",
    "price": 24,
    "meal": "dinner",
    "course": "main",
    "item_id": 3017
  },
  {
    "item": "panang curry of lamb shank",
    "description": "thai basil, roasted shallot, peanut",
    "price": 23,
    "meal": "dinner",
    "course": "main",
    "item_id": 3018
  },
  {
    "item": "southern style red curry of seafood",
    "description": "rich and aromatic, array of seafood, young coconut, betal leaf",
    "price": 23,
    "meal": "dinner",
    "course": "main",
    "item_id": 3019
  },
  {
    "item": "hand made roti",
    "description": "",
    "price": 4,
    "meal": "dinner",
    "course": "side",
    "item_id": 3020
  },
  {
    "item": "peanut sauce",
    "description": "",
    "price": 3,
    "meal": "dinner",
    "course": "side",
    "item_id": 3021
  },
  {
    "item": "steamed jasmine rice",
    "description": "",
    "price": 3,
    "meal": "dinner",
    "course": "side",
    "item_id": 3022
  }
]